<?xml version="1.0" encoding="utf-8"?>
<ModReplacement>
  <Author>Tarojun</Author>
  <ModId>
  </ModId>
  <ModName>Vanilla insect meat meals</ModName>
  <ReplacementAuthor>velcroboy333</ReplacementAuthor>
  <ReplacementModId>InsectMeatMeals.velcroboy333</ReplacementModId>
  <ReplacementName>Vanilla insect meat meals(continued)</ReplacementName>
  <ReplacementSteamId>2094279970</ReplacementSteamId>
  <SteamId>1837799521</SteamId>
  <Versions>1.0</Versions>
  <ReplacementVersions>1.0,1.1,1.2,1.3,1.4,1.5</ReplacementVersions>
</ModReplacement>
