<?xml version="1.0" encoding="utf-8"?>
<ModReplacement>
  <Author>Pooler</Author>
  <ModId>CEC.CombatEnthuCore</ModId>
  <ModName>[1.1] Combat Enthusiast's Collection</ModName>
  <ReplacementAuthor>Mlie</ReplacementAuthor>
  <ReplacementModId>Mlie.CombatEnthusiastsCollection</ReplacementModId>
  <ReplacementName>Combat Enthusiast's Collection (Continued)</ReplacementName>
  <ReplacementSteamId>2847283634</ReplacementSteamId>
  <SteamId>1862509294</SteamId>
  <Versions>1.0,1.1</Versions>
  <ReplacementVersions>1.0,1.1,1.2,1.3,1.4,1.5</ReplacementVersions>
</ModReplacement>
