<?xml version="1.0" encoding="utf-8"?>
<ModReplacement>
  <Author>WolfgangPolska/ Nero the Fam</Author>
  <ModId>Yuno.SimpleOresTest</ModId>
  <ModName>Simple Mining Extension</ModName>
  <ReplacementAuthor>Mlie</ReplacementAuthor>
  <ReplacementModId>Mlie.SimpleMiningExtension</ReplacementModId>
  <ReplacementName>Simple Mining Extension (Continued)</ReplacementName>
  <ReplacementSteamId>2819002574</ReplacementSteamId>
  <SteamId>2000091253</SteamId>
  <Versions>1.0,1.1,1.2</Versions>
  <ReplacementVersions>1.0,1.1,1.2,1.3,1.4,1.5</ReplacementVersions>
</ModReplacement>
