<?xml version="1.0" encoding="utf-8"?>
<ModReplacement>
  <Author>Mlie</Author>
  <ModId>Mlie.ScenarioAmender</ModId>
  <ModName>Scenario Amender (Continued)</ModName>
  <ReplacementAuthor>*katana</ReplacementAuthor>
  <ReplacementModId>katana.scenarioamender</ReplacementModId>
  <ReplacementName>Scenario Amender [1.5]</ReplacementName>
  <ReplacementSteamId>3236547440</ReplacementSteamId>
  <SteamId>2201715440</SteamId>
  <Versions>1.1,1.2,1.3</Versions>
  <ReplacementVersions>1.5</ReplacementVersions>
</ModReplacement>
