<?xml version="1.0" encoding="utf-8"?>
<ModReplacement>
  <Author>MrKociak</Author>
  <ModId>MrKociak.MAGFragmentCrafting</ModId>
  <ModName>More Archotech Garbage - craftable fragments</ModName>
  <ReplacementAuthor>Zaljerem</ReplacementAuthor>
  <ReplacementModId>zal.magfragmentcrafting</ReplacementModId>
  <ReplacementName>More Archotech Garbage - Craftable Fragments (Continued)</ReplacementName>
  <ReplacementSteamId>3241945459</ReplacementSteamId>
  <SteamId>2520917759</SteamId>
  <Versions>1.2,1.3</Versions>
  <ReplacementVersions>1.4,1.5</ReplacementVersions>
</ModReplacement>
