<?xml version="1.0" encoding="utf-8"?>
<LanguageData>
  <!--The following translations were generated by https://www.deepl.com/-->
  <UTI.veboseLogging>冗长日志记录</UTI.veboseLogging>
  <UTI.veboseLoggingtt>主要用于调试</UTI.veboseLoggingtt>
  <UTI.author>由</UTI.author>
  <UTI.replace>更换模式</UTI.replace>
  <UTI.modlistChanged>修改列表已更新，关闭此窗口时需要重新启动</UTI.modlistChanged>
  <UTI.subscribing>以 Steam-id {1} 订阅 {0}</UTI.subscribing>
  <UTI.subscribed>订阅了 {0}</UTI.subscribed>
  <UTI.unsubscribing>用 Steam-id {1} 取消订阅 {0}</UTI.unsubscribing>
  <UTI.unsubscribed>取消订阅 {0}</UTI.unsubscribed>
  <UTI.failedToSubscribe>使用 Steam-id {1} 订阅 {0} 失败</UTI.failedToSubscribe>
  <UTI.failedToUnsubscribe>退订 Steam-id {1} 的 {0} 失败</UTI.failedToUnsubscribe>
  <UTI.alreadyReplacing>正在更换一个模块，请等待完成</UTI.alreadyReplacing>
  <UTI.restartNeeded>关闭时将重新启动</UTI.restartNeeded>
  <UTI.stillWaiting>等待模式下载，一分钟后超时</UTI.stillWaiting>
  <UTI.modReplaced>将"{0}"替换为"{1}"</UTI.modReplaced>
  <UTI.foundReplacements>找到替代品：{0}</UTI.foundReplacements>
  <UTI.modVersion>已安装模块版本：{0}</UTI.modVersion>
  <UTI.replacements>{0}替换</UTI.replacements>
  <UTI.checkingAll>检查所有修改器</UTI.checkingAll>
  <UTI.checkingEnabled>检查已启用的修改器</UTI.checkingEnabled>
  <UTI.allMods>检查所有修改</UTI.allMods>
  <UTI.allModstt>将检查所有已安装的多器官功能障碍以进行替换，而不是只检查当前加载的多器官功能障碍</UTI.allModstt>
  <UTI.alwaysShow>始终显示更换按钮</UTI.alwaysShow>
  <UTI.alwaysShowtt>即使没有找到替代品，也会显示打开替换窗口的按钮</UTI.alwaysShowtt>
  <UTI.notUpdated>注意：替换版本不支持此版本的《环游世界》（{0}）。</UTI.notUpdated>
  <UTI.replaceMod>原创
{0}
作者：{2}
版本：{4}

替换
{1}
作者： {3}{3}
版本：{5}</UTI.replaceMod>
  <UTI.replaceModActive>原创
{0}
作者：{2}
版本：{4}

替换
{1}
作者： {3}{3}
版本：{5}

注意：由于该 MOD 当前处于激活状态，因此当您关闭替换列表以应用新的 MOD 时，将会触发重启。</UTI.replaceModActive>
  <UTI.waitingUnsub>等待蒸汽处理退订</UTI.waitingUnsub>
  <UTI.waitingSub>等待蒸汽处理订阅</UTI.waitingSub>
  <UTI.activeModsChanged>活动模式已更改，重启前打开模式配置以启用和排序</UTI.activeModsChanged>
  <UTI.activatingMods>在活动模式列表中添加新模式</UTI.activatingMods>
  <UTI.incompatibility>{0}与激活的模式不兼容：{0}</UTI.incompatibility>
  <UTI.checkingRequirements>检查先决条件是否已安装</UTI.checkingRequirements>
  <UTI.replacementStatus>更换进度</UTI.replacementStatus>
  <UTI.showingRelevant>显示相关替换</UTI.showingRelevant>
  <UTI.showingAll>显示所有替换</UTI.showingAll>
  <UTI.onlyRelevantInfo>只显示兼容的替代品</UTI.onlyRelevantInfo>
  <UTI.onlyRelevant>只显示兼容的替代品</UTI.onlyRelevant>
  <UTI.onlyRelevanttt>不显示不支持已安装游戏版本的替代品</UTI.onlyRelevanttt>
  <UTI.steamMod>模式从 Steam 模式文件夹加载</UTI.steamMod>
  <UTI.localMod>模块从本地模块文件夹加载</UTI.localMod>
  <UTI.cantUnsubscribe>{0}是本地模式，跳过取消订阅</UTI.cantUnsubscribe>
  <UTI.preferOverlay>首选蒸汽叠加链接</UTI.preferOverlay>
  <UTI.preferOverlaytt>打开 MOD 网页时，优先选择在 Steam 叠加而不是默认浏览器中启动它</UTI.preferOverlaytt>
  <UTI.replacing>替换 {0}（{2}的模式 {1）</UTI.replacing>
  <UTI.selectNone>无</UTI.selectNone>
  <UTI.selectAll>选择所有</UTI.selectAll>
  <UTI.updateSelected>更新{0}个选定模式</UTI.updateSelected>
  <UTI.replaceMultipleMods>替换 {0} 模式？</UTI.replaceMultipleMods>
  <UTI.replaceMultipleModsActive>替换 {0} 模式？

注意：由于当前有一个或多个模式处于激活状态，因此在对新模式进行排序后关闭模式窗口时将触发重启。</UTI.replaceMultipleModsActive>
</LanguageData>
